agora_utils/__init__.py
agora_utils/_version.py
agora_utils/agora_time.py
agora_utils/version.py
agora_utils-3.0.2.dist-info/licenses/LICENSE
agora_utils-3.0.2.dist-info/WHEEL
agora_utils-3.0.2.dist-info/METADATA
agora_utils-3.0.2.dist-info/RECORD
