Metadata-Version: 2.4
Name: agora_utils
Version: 3.0.2
Summary: Utilities libraries for the Agora Edge Apps SDK 2.0 (Python)
Author-email: AgoraIoT <agoraiot@slb.com>
Classifier: License :: OSI Approved :: Apache Software License
License-File: LICENSE
Project-URL: Home, https://agoraiot.github.io
